README.rst
setup.cfg
setup.py
tests/__init__.py
tests/test_server.py
websocket_redis/__init__.py
websocket_redis.egg-info/PKG-INFO
websocket_redis.egg-info/SOURCES.txt
websocket_redis.egg-info/dependency_links.txt
websocket_redis.egg-info/entry_points.txt
websocket_redis.egg-info/requires.txt
websocket_redis.egg-info/top_level.txt
websocket_redis/api/__init__.py
websocket_redis/api/abstract_listener.py
websocket_redis/api/abstract_message.py
websocket_redis/api/async/__init__.py
websocket_redis/api/async/listener.py
websocket_redis/api/async/message.py
websocket_redis/api/threading/__init__.py
websocket_redis/api/threading/listener.py
websocket_redis/api/threading/message.py
websocket_redis/common/__init__.py
websocket_redis/common/compatibility.py
websocket_redis/common/redis_manager.py
websocket_redis/common/aioredis/__init__.py
websocket_redis/common/aioredis/aioredis_manager.py
websocket_redis/server/__init__.py
websocket_redis/server/ws_handler.py
websocket_redis/server/ws_server.py