Metadata-Version: 1.1
Name: websocket-redis
Version: 0.1.0
Summary: Communicate with websocket through redis as messaging broker
Home-page: https://github.com/Abdeljelil/websocket_redis
Author: Mohamed abdeljelil
Author-email: abdeljelil.mohamed@gmail.com
License: BSD
Download-URL: https://github.com/Abdeljelil/websocket_redis.git
Keywords: python websocket redis asyncio
Platform: UNKNOWN
Classifier: Development Status :: 3 - Alpha
Classifier: Intended Audience :: Developers
Classifier: Natural Language :: English
Classifier: Operating System :: Unix
Classifier: Programming Language :: Python :: 2.7
Classifier: Programming Language :: Python :: 3.4
Classifier: Programming Language :: Python :: 3.5
